[{"team":"Morgantown Redbirds 11U - 2026","number":10,"player":"Trent C","g":19,"ip":63.1,"h":61,"r":27,"er":23,"bb":10,"so":49,"pitches":764,"strikes":528,"bf":253,"era":2.18,"whip":1.12,"strike%":0.691},{"team":"Mon River Mudcats 11U","number":23,"player":"JP M","g":22,"ip":56.1,"h":72,"r":74,"er":52,"bb":33,"so":40,"pitches":827,"strikes":459,"bf":244,"era":5.54,"whip":1.86,"strike%":0.555},{"team":"Morgantown Redbirds 11U - 2026","number":14,"player":"Brecken D","g":11,"ip":42.2,"h":44,"r":23,"er":18,"bb":24,"so":33,"pitches":677,"strikes":389,"bf":187,"era":2.53,"whip":1.59,"strike%":0.575},{"team":"Morgantown Redbirds 11U - 2026","number":16,"player":"Hunter W","g":15,"ip":36.2,"h":34,"r":19,"er":16,"bb":9,"so":29,"pitches":459,"strikes":315,"bf":145,"era":2.62,"whip":1.17,"strike%":0.686},{"team":"Morgantown Mambas 11U","number":12,"player":"Giulio P","g":14,"ip":36.0,"h":55,"r":79,"er":66,"bb":56,"so":46,"pitches":868,"strikes":455,"bf":220,"era":11.0,"whip":3.08,"strike%":0.524},{"team":"Morgantown Redbirds 11U - 2026","number":18,"player":"Brennan S","g":18,"ip":36.0,"h":33,"r":26,"er":22,"bb":15,"so":33,"pitches":462,"strikes":294,"bf":142,"era":3.67,"whip":1.33,"strike%":0.636},{"team":"Covered Bridge RiverJaxx 11U","number":10,"player":"Sawyer M","g":11,"ip":33.2,"h":40,"r":43,"er":37,"bb":27,"so":33,"pitches":554,"strikes":295,"bf":138,"era":6.59,"whip":1.99,"strike%":0.532},{"team":"Mon River Mudcats 11U","number":18,"player":"Cade H","g":20,"ip":33.1,"h":46,"r":58,"er":44,"bb":49,"so":33,"pitches":737,"strikes":357,"bf":173,"era":7.92,"whip":2.85,"strike%":0.484},{"team":"Covered Bridge RiverJaxx 11U","number":20,"player":"Bryson W","g":10,"ip":30.2,"h":39,"r":23,"er":21,"bb":7,"so":29,"pitches":426,"strikes":289,"bf":120,"era":4.11,"whip":1.5,"strike%":0.678},{"team":"Covered Bridge RiverJaxx 11U","number":4,"player":"Jase M","g":8,"ip":30.0,"h":34,"r":38,"er":26,"bb":20,"so":20,"pitches":498,"strikes":277,"bf":131,"era":5.2,"whip":1.8,"strike%":0.556},{"team":"Covered Bridge RiverJaxx 11U","number":11,"player":"Levi A","g":13,"ip":29.1,"h":41,"r":35,"er":34,"bb":20,"so":17,"pitches":399,"strikes":216,"bf":117,"era":6.95,"whip":2.08,"strike%":0.541},{"team":"Morgantown Redbirds 11U - 2026","number":11,"player":"Bradley W","g":12,"ip":29.0,"h":26,"r":17,"er":12,"bb":15,"so":33,"pitches":463,"strikes":272,"bf":122,"era":2.48,"whip":1.41,"strike%":0.587},{"team":"Morgantown Redbirds 11U - 2026","number":8,"player":"Calvin W","g":11,"ip":29.0,"h":35,"r":22,"er":16,"bb":8,"so":22,"pitches":421,"strikes":285,"bf":124,"era":3.31,"whip":1.48,"strike%":0.677},{"team":"Covered Bridge RiverJaxx 11U","number":21,"player":"Vance H","g":14,"ip":28.1,"h":43,"r":41,"er":27,"bb":28,"so":12,"pitches":497,"strikes":271,"bf":145,"era":5.72,"whip":2.51,"strike%":0.545},{"team":"Covered Bridge RiverJaxx 11U","number":8,"player":"Wyatt F","g":13,"ip":27.2,"h":37,"r":41,"er":28,"bb":26,"so":17,"pitches":437,"strikes":231,"bf":119,"era":6.07,"whip":2.28,"strike%":0.529},{"team":"Covered Bridge RiverJaxx 11U","number":29,"player":"Bryce H","g":12,"ip":27.1,"h":25,"r":28,"er":19,"bb":19,"so":18,"pitches":391,"strikes":218,"bf":96,"era":4.17,"whip":1.61,"strike%":0.558},{"team":"Hit Dogs Bridgeport 11U","number":74,"player":"Rowan D","g":9,"ip":27.0,"h":51,"r":65,"er":44,"bb":23,"so":34,"pitches":517,"strikes":282,"bf":144,"era":9.78,"whip":2.74,"strike%":0.545},{"team":"Mon River Mudcats 11U","number":9,"player":"Kolston A","g":13,"ip":26.0,"h":27,"r":35,"er":20,"bb":19,"so":21,"pitches":411,"strikes":219,"bf":106,"era":4.62,"whip":1.77,"strike%":0.533},{"team":"Morgantown Redbirds 11U - 2026","number":25,"player":"Logan C","g":11,"ip":24.2,"h":23,"r":20,"er":16,"bb":17,"so":24,"pitches":388,"strikes":225,"bf":105,"era":3.89,"whip":1.62,"strike%":0.58},{"team":"Fayette Fury 11U","number":9,"player":"Elisha M","g":9,"ip":24.1,"h":26,"r":32,"er":29,"bb":27,"so":23,"pitches":400,"strikes":202,"bf":101,"era":7.15,"whip":2.18,"strike%":0.505},{"team":"Mon River Mudcats 11U","number":31,"player":"Maddox E","g":13,"ip":24.0,"h":29,"r":39,"er":30,"bb":28,"so":22,"pitches":436,"strikes":213,"bf":110,"era":7.5,"whip":2.38,"strike%":0.489},{"team":"Hit Dogs Bridgeport 11U","number":50,"player":"Asher H","g":9,"ip":23.0,"h":49,"r":72,"er":59,"bb":32,"so":14,"pitches":453,"strikes":230,"bf":137,"era":15.39,"whip":3.52,"strike%":0.508},{"team":"Morgantown Mambas 11U","number":11,"player":"Jaxon P","g":12,"ip":22.2,"h":57,"r":56,"er":47,"bb":23,"so":20,"pitches":484,"strikes":266,"bf":136,"era":12.44,"whip":3.53,"strike%":0.55},{"team":"Fayette Fury 11U","number":11,"player":"Fletcher J","g":11,"ip":22.0,"h":45,"r":44,"er":34,"bb":15,"so":9,"pitches":352,"strikes":190,"bf":107,"era":9.27,"whip":2.73,"strike%":0.54},{"team":"Morgantown Redbirds 11U - 2026","number":30,"player":"Jakeob E","g":16,"ip":22.0,"h":15,"r":19,"er":18,"bb":14,"so":24,"pitches":401,"strikes":237,"bf":99,"era":4.91,"whip":1.32,"strike%":0.591},{"team":"Fayette Fury 11U","number":25,"player":"Hudson P","g":7,"ip":20.1,"h":24,"r":13,"er":12,"bb":5,"so":21,"pitches":299,"strikes":184,"bf":82,"era":3.54,"whip":1.43,"strike%":0.615},{"team":"Morgantown Mambas 11U","number":18,"player":"Keaton G","g":13,"ip":20.1,"h":64,"r":74,"er":67,"bb":31,"so":30,"pitches":561,"strikes":297,"bf":145,"era":19.77,"whip":4.67,"strike%":0.529},{"team":"Mon River Mudcats 11U","number":3,"player":"Matthias R","g":11,"ip":17.2,"h":30,"r":54,"er":47,"bb":30,"so":19,"pitches":418,"strikes":195,"bf":103,"era":15.96,"whip":3.4,"strike%":0.467},{"team":"Mon River Mudcats 11U","number":32,"player":"Camden B","g":7,"ip":16.1,"h":23,"r":29,"er":24,"bb":23,"so":16,"pitches":347,"strikes":174,"bf":91,"era":8.82,"whip":2.82,"strike%":0.501},{"team":"Hit Dogs Bridgeport 11U","number":7,"player":"Trey S","g":7,"ip":15.0,"h":31,"r":30,"er":24,"bb":15,"so":12,"pitches":310,"strikes":174,"bf":89,"era":9.6,"whip":3.07,"strike%":0.561},{"team":"Morgantown Mambas 11U","number":10,"player":"Cohen C","g":6,"ip":14.2,"h":26,"r":37,"er":30,"bb":20,"so":3,"pitches":267,"strikes":119,"bf":79,"era":12.27,"whip":3.14,"strike%":0.446},{"team":"Fayette Fury 11U","number":1,"player":"Landon B","g":7,"ip":14.1,"h":13,"r":10,"er":9,"bb":11,"so":17,"pitches":226,"strikes":123,"bf":61,"era":3.77,"whip":1.67,"strike%":0.544},{"team":"Fayette Fury 11U","number":14,"player":"Dylan P","g":6,"ip":14.1,"h":20,"r":13,"er":13,"bb":8,"so":8,"pitches":207,"strikes":127,"bf":63,"era":5.44,"whip":1.95,"strike%":0.614},{"team":"Morgantown Mambas 11U","number":23,"player":"Carson S","g":8,"ip":14.1,"h":21,"r":31,"er":29,"bb":26,"so":8,"pitches":283,"strikes":125,"bf":80,"era":12.14,"whip":3.28,"strike%":0.442},{"team":"Hit Dogs Bridgeport 11U","number":45,"player":"Kellan E","g":6,"ip":11.2,"h":11,"r":16,"er":14,"bb":11,"so":6,"pitches":179,"strikes":92,"bf":46,"era":7.2,"whip":1.89,"strike%":0.514},{"team":"Covered Bridge RiverJaxx 11U","number":3,"player":"Jonah M","g":6,"ip":11.1,"h":13,"r":13,"er":11,"bb":12,"so":8,"pitches":234,"strikes":119,"bf":58,"era":5.82,"whip":2.21,"strike%":0.509},{"team":"Hit Dogs Bridgeport 11U","number":17,"player":"Colby M","g":4,"ip":11.1,"h":14,"r":21,"er":15,"bb":12,"so":14,"pitches":239,"strikes":129,"bf":57,"era":7.94,"whip":2.29,"strike%":0.54},{"team":"Hit Dogs Bridgeport 11U","number":9,"player":"Maddox M","g":5,"ip":11.1,"h":17,"r":22,"er":19,"bb":15,"so":9,"pitches":211,"strikes":105,"bf":59,"era":10.06,"whip":2.82,"strike%":0.498},{"team":"Morgantown Redbirds 11U - 2026","number":13,"player":"Dominic R","g":5,"ip":10.1,"h":8,"r":5,"er":3,"bb":2,"so":9,"pitches":137,"strikes":89,"bf":35,"era":1.74,"whip":0.97,"strike%":0.65},{"team":"Morgantown Mambas 11U","number":7,"player":"Cooper L","g":6,"ip":10.0,"h":25,"r":17,"er":16,"bb":3,"so":8,"pitches":171,"strikes":110,"bf":61,"era":9.6,"whip":2.8,"strike%":0.643},{"team":"Mon River Mudcats 11U","number":1,"player":"Jordan M","g":4,"ip":9.1,"h":11,"r":11,"er":9,"bb":9,"so":3,"pitches":141,"strikes":70,"bf":40,"era":5.79,"whip":2.14,"strike%":0.496},{"team":"Mon River Mudcats 11U","number":20,"player":"Logan B","g":6,"ip":9.0,"h":22,"r":22,"er":22,"bb":8,"so":5,"pitches":142,"strikes":71,"bf":45,"era":14.67,"whip":3.33,"strike%":0.5},{"team":"Morgantown Redbirds 11U - 2026","number":2,"player":"Rocco D","g":9,"ip":9.0,"h":13,"r":17,"er":14,"bb":10,"so":3,"pitches":159,"strikes":79,"bf":46,"era":9.33,"whip":2.56,"strike%":0.497},{"team":"Morgantown Mambas 11U","number":4,"player":"Liam P","g":4,"ip":8.2,"h":7,"r":7,"er":4,"bb":5,"so":3,"pitches":95,"strikes":48,"bf":27,"era":2.77,"whip":1.38,"strike%":0.505},{"team":"Covered Bridge RiverJaxx 11U","number":9,"player":"Koop C","g":4,"ip":7.0,"h":17,"r":8,"er":8,"bb":4,"so":9,"pitches":131,"strikes":78,"bf":40,"era":6.86,"whip":3.0,"strike%":0.595},{"team":"Hit Dogs Bridgeport 11U","number":27,"player":"Nolan M","g":3,"ip":6.2,"h":4,"r":10,"er":10,"bb":10,"so":3,"pitches":91,"strikes":38,"bf":23,"era":9.0,"whip":2.1,"strike%":0.418},{"team":"Mon River Mudcats 11U","number":22,"player":"Tristian H","g":4,"ip":5.1,"h":7,"r":14,"er":11,"bb":9,"so":2,"pitches":97,"strikes":41,"bf":26,"era":12.38,"whip":3.0,"strike%":0.423},{"team":"Covered Bridge RiverJaxx 11U","number":22,"player":"Grayson W","g":3,"ip":4.0,"h":5,"r":5,"er":3,"bb":4,"so":1,"pitches":73,"strikes":33,"bf":18,"era":4.5,"whip":2.25,"strike%":0.452},{"team":"Fayette Fury 11U","number":10,"player":"Abe T","g":4,"ip":4.0,"h":21,"r":20,"er":20,"bb":4,"so":2,"pitches":113,"strikes":64,"bf":34,"era":30.0,"whip":6.25,"strike%":0.566},{"team":"Morgantown Redbirds 11U - 2026","number":77,"player":"Colin K","g":1,"ip":4.0,"h":9,"r":6,"er":6,"bb":2,"so":3,"pitches":73,"strikes":50,"bf":22,"era":9.0,"whip":2.75,"strike%":0.685},{"team":"Fayette Fury 11U","number":22,"player":"Richie B","g":1,"ip":2.1,"h":2,"r":5,"er":5,"bb":4,"so":1,"pitches":39,"strikes":13,"bf":8,"era":12.86,"whip":2.57,"strike%":0.333},{"team":"Mon River Mudcats 11U","number":14,"player":"Landen B","g":1,"ip":2.1,"h":0,"r":3,"er":1,"bb":4,"so":0,"pitches":28,"strikes":8,"bf":6,"era":2.57,"whip":1.71,"strike%":0.286},{"team":"Morgantown Mambas 11U","number":1,"player":"Grayson W","g":1,"ip":2.1,"h":3,"r":5,"er":5,"bb":2,"so":0,"pitches":30,"strikes":12,"bf":7,"era":12.86,"whip":2.14,"strike%":0.4},{"team":"Hit Dogs Bridgeport 11U","number":2,"player":"Camden F","g":2,"ip":2.0,"h":0,"r":3,"er":3,"bb":4,"so":2,"pitches":27,"strikes":10,"bf":8,"era":9.0,"whip":2.0,"strike%":0.37},{"team":"Hit Dogs Bridgeport 11U","number":44,"player":"Hank M","g":3,"ip":2.0,"h":5,"r":7,"er":0,"bb":3,"so":0,"pitches":48,"strikes":26,"bf":16,"era":0.0,"whip":4.0,"strike%":0.542},{"team":"Covered Bridge RiverJaxx 11U","number":13,"player":"Cohen F","g":1,"ip":1.0,"h":0,"r":0,"er":0,"bb":2,"so":3,"pitches":29,"strikes":13,"bf":5,"era":0.0,"whip":2.0,"strike%":0.448},{"team":"Fayette Fury 11U","number":85,"player":"Camden B","g":1,"ip":1.0,"h":0,"r":0,"er":0,"bb":1,"so":1,"pitches":14,"strikes":7,"bf":4,"era":0.0,"whip":1.0,"strike%":0.5},{"team":"Fayette Fury 11U","number":23,"player":"Logan G","g":1,"ip":1.0,"h":0,"r":0,"er":0,"bb":0,"so":0,"pitches":9,"strikes":5,"bf":3,"era":0.0,"whip":0.0,"strike%":0.556},{"team":"Fayette Fury 11U","number":13,"player":"Brady H","g":1,"ip":1.0,"h":4,"r":4,"er":4,"bb":1,"so":1,"pitches":21,"strikes":13,"bf":8,"era":24.0,"whip":5.0,"strike%":0.619},{"team":"Morgantown Mambas 11U","number":77,"player":"Kolsen C","g":2,"ip":1.0,"h":5,"r":10,"er":10,"bb":8,"so":2,"pitches":67,"strikes":24,"bf":16,"era":60.0,"whip":13.0,"strike%":0.358}]