[{"team":"Morgantown Redbirds (2026) 9U","number":17,"player":"Owen B","games_pitched":2,"ip":1.1,"h":1,"r":0,"er":0,"bb":1,"so":0,"pitches":16,"strikes":8,"batters_faced":6,"era":0.0,"whip":1.5,"strike_pct":0.5},{"team":"WV Miners","number":13,"player":"Noah N","games_pitched":1,"ip":1.0,"h":0,"r":0,"er":0,"bb":2,"so":2,"pitches":27,"strikes":12,"batters_faced":5,"era":0.0,"whip":2.0,"strike_pct":0.444},{"team":"Mon River Mudcats 9U","number":17,"player":"Lucas S","games_pitched":3,"ip":7.0,"h":7,"r":4,"er":2,"bb":3,"so":9,"pitches":115,"strikes":65,"batters_faced":31,"era":1.71,"whip":1.43,"strike_pct":0.565},{"team":"Morgantown Redbirds (2026) 9U","number":2,"player":"Eli E","games_pitched":10,"ip":21.1,"h":15,"r":10,"er":9,"bb":8,"so":29,"pitches":327,"strikes":197,"batters_faced":85,"era":2.53,"whip":1.08,"strike_pct":0.602},{"team":"2026 Covered Bridge Riverjaxx 9U","number":22,"player":"Jase R","games_pitched":2,"ip":2.1,"h":4,"r":1,"er":1,"bb":1,"so":4,"pitches":39,"strikes":26,"batters_faced":11,"era":2.57,"whip":2.14,"strike_pct":0.667},{"team":"2026 Covered Bridge Riverjaxx 9U","number":50,"player":"Luca J","games_pitched":16,"ip":25.2,"h":33,"r":22,"er":12,"bb":20,"so":34,"pitches":492,"strikes":279,"batters_faced":127,"era":2.81,"whip":2.06,"strike_pct":0.567},{"team":"WV Patriots","number":17,"player":"Parker I","games_pitched":14,"ip":30.1,"h":35,"r":27,"er":15,"bb":23,"so":37,"pitches":558,"strikes":331,"batters_faced":155,"era":2.97,"whip":1.91,"strike_pct":0.593},{"team":"Morgantown Redbirds (2026) 9U","number":99,"player":"Logan B","games_pitched":14,"ip":28.1,"h":34,"r":17,"er":17,"bb":13,"so":37,"pitches":476,"strikes":295,"batters_faced":128,"era":3.6,"whip":1.66,"strike_pct":0.62},{"team":"WV Patriots","number":15,"player":"Ryan T","games_pitched":1,"ip":3.1,"h":4,"r":2,"er":2,"bb":0,"so":1,"pitches":36,"strikes":28,"batters_faced":14,"era":3.6,"whip":1.2,"strike_pct":0.778},{"team":"WV Patriots","number":3,"player":"Atlas A","games_pitched":12,"ip":24.2,"h":27,"r":21,"er":17,"bb":14,"so":19,"pitches":378,"strikes":238,"batters_faced":114,"era":4.14,"whip":1.66,"strike_pct":0.63},{"team":"Mon River Mudcats 9U","number":13,"player":"Brayton A","games_pitched":1,"ip":1.1,"h":1,"r":1,"er":1,"bb":2,"so":0,"pitches":23,"strikes":13,"batters_faced":9,"era":4.5,"whip":2.25,"strike_pct":0.565},{"team":"WV Patriots","number":6,"player":"Cannon H","games_pitched":12,"ip":22.1,"h":20,"r":25,"er":18,"bb":17,"so":29,"pitches":416,"strikes":245,"batters_faced":111,"era":4.84,"whip":1.66,"strike_pct":0.589},{"team":"WV Patriots","number":23,"player":"Anthony D","games_pitched":11,"ip":27.0,"h":22,"r":34,"er":23,"bb":31,"so":50,"pitches":578,"strikes":304,"batters_faced":140,"era":5.11,"whip":1.96,"strike_pct":0.526},{"team":"Morgantown Redbirds (2026) 9U","number":11,"player":"Gus R","games_pitched":13,"ip":19.2,"h":22,"r":17,"er":17,"bb":24,"so":22,"pitches":397,"strikes":203,"batters_faced":101,"era":5.19,"whip":2.34,"strike_pct":0.511},{"team":"Mon River Mudcats 9U","number":2,"player":"Jaxon A","games_pitched":6,"ip":8.0,"h":11,"r":7,"er":7,"bb":5,"so":8,"pitches":157,"strikes":90,"batters_faced":40,"era":5.25,"whip":2.0,"strike_pct":0.573},{"team":"WV Patriots","number":33,"player":"Tripp H","games_pitched":4,"ip":5.2,"h":2,"r":6,"er":5,"bb":6,"so":8,"pitches":102,"strikes":51,"batters_faced":28,"era":5.29,"whip":1.41,"strike_pct":0.5},{"team":"Mon River Mudcats 9U","number":1,"player":"Cole D","games_pitched":11,"ip":14.2,"h":19,"r":24,"er":13,"bb":20,"so":26,"pitches":344,"strikes":186,"batters_faced":90,"era":5.32,"whip":2.66,"strike_pct":0.541},{"team":"Morgantown Redbirds (2026) 9U","number":6,"player":"Clayton T","games_pitched":12,"ip":32.1,"h":43,"r":34,"er":30,"bb":13,"so":53,"pitches":572,"strikes":367,"batters_faced":157,"era":5.57,"whip":1.73,"strike_pct":0.642},{"team":"WV Patriots","number":12,"player":"Weston K","games_pitched":5,"ip":9.1,"h":12,"r":10,"er":9,"bb":8,"so":11,"pitches":183,"strikes":109,"batters_faced":49,"era":5.79,"whip":2.14,"strike_pct":0.596},{"team":"WV Patriots","number":44,"player":"Trent M","games_pitched":13,"ip":23.0,"h":25,"r":32,"er":23,"bb":25,"so":26,"pitches":441,"strikes":249,"batters_faced":124,"era":6.0,"whip":2.17,"strike_pct":0.565},{"team":"Morgantown Mambas (Gold) 9U","number":16,"player":"Thayden Olesh","games_pitched":2,"ip":2.0,"h":3,"r":2,"er":2,"bb":4,"so":5,"pitches":59,"strikes":30,"batters_faced":13,"era":6.0,"whip":3.5,"strike_pct":0.508},{"team":"Morgantown Mambas (Gold) 9U","number":10,"player":"Stellan Harris","games_pitched":15,"ip":20.0,"h":28,"r":21,"er":21,"bb":28,"so":25,"pitches":471,"strikes":245,"batters_faced":113,"era":6.3,"whip":2.8,"strike_pct":0.52},{"team":"Mon River Mudcats 9U","number":14,"player":"Nash M","games_pitched":16,"ip":30.0,"h":37,"r":34,"er":32,"bb":27,"so":43,"pitches":597,"strikes":320,"batters_faced":162,"era":6.4,"whip":2.13,"strike_pct":0.536},{"team":"Mon River Mudcats 9U","number":55,"player":"Nicholas P","games_pitched":16,"ip":25.2,"h":36,"r":42,"er":28,"bb":32,"so":45,"pitches":556,"strikes":310,"batters_faced":151,"era":6.55,"whip":2.65,"strike_pct":0.558},{"team":"Morgantown Redbirds (2026) 9U","number":23,"player":"Jack P","games_pitched":16,"ip":35.1,"h":52,"r":42,"er":41,"bb":19,"so":49,"pitches":650,"strikes":412,"batters_faced":173,"era":6.96,"whip":2.01,"strike_pct":0.634},{"team":"WV Miners","number":23,"player":"Jack K","games_pitched":9,"ip":17.0,"h":30,"r":23,"er":20,"bb":17,"so":29,"pitches":393,"strikes":224,"batters_faced":99,"era":7.06,"whip":2.76,"strike_pct":0.57},{"team":"Mon River Mudcats 9U","number":21,"player":"Kolton R","games_pitched":10,"ip":18.2,"h":27,"r":34,"er":22,"bb":28,"so":29,"pitches":448,"strikes":226,"batters_faced":119,"era":7.07,"whip":2.95,"strike_pct":0.504},{"team":"2026 Covered Bridge Riverjaxx 9U","number":9,"player":"Colton C","games_pitched":16,"ip":30.1,"h":46,"r":38,"er":37,"bb":26,"so":40,"pitches":606,"strikes":345,"batters_faced":159,"era":7.32,"whip":2.37,"strike_pct":0.569},{"team":"Morgantown Redbirds (2026) 9U","number":7,"player":"Bryce P","games_pitched":13,"ip":26.0,"h":37,"r":33,"er":33,"bb":16,"so":28,"pitches":466,"strikes":262,"batters_faced":130,"era":7.62,"whip":2.04,"strike_pct":0.562},{"team":"Morgantown Redbirds (2026) 9U","number":44,"player":"Finn C","games_pitched":10,"ip":20.1,"h":31,"r":26,"er":26,"bb":13,"so":19,"pitches":355,"strikes":215,"batters_faced":105,"era":7.67,"whip":2.16,"strike_pct":0.606},{"team":"Mon River Mudcats 9U","number":5,"player":"William R","games_pitched":4,"ip":4.2,"h":8,"r":6,"er":6,"bb":2,"so":6,"pitches":73,"strikes":52,"batters_faced":24,"era":7.71,"whip":2.14,"strike_pct":0.712},{"team":"WV Miners","number":22,"player":"Holden S","games_pitched":9,"ip":15.0,"h":25,"r":22,"er":20,"bb":16,"so":15,"pitches":324,"strikes":154,"batters_faced":85,"era":8.0,"whip":2.73,"strike_pct":0.475},{"team":"2026 Covered Bridge Riverjaxx 9U","number":13,"player":"Kanon B","games_pitched":11,"ip":17.2,"h":23,"r":24,"er":24,"bb":22,"so":24,"pitches":369,"strikes":194,"batters_faced":98,"era":8.15,"whip":2.55,"strike_pct":0.526},{"team":"Morgantown Redbirds (2026) 9U","number":10,"player":"Landry O","games_pitched":8,"ip":17.0,"h":25,"r":25,"er":24,"bb":21,"so":26,"pitches":377,"strikes":212,"batters_faced":99,"era":8.47,"whip":2.71,"strike_pct":0.562},{"team":"2026 Covered Bridge Riverjaxx 9U","number":1,"player":"Brently W","games_pitched":14,"ip":28.1,"h":47,"r":45,"er":42,"bb":34,"so":38,"pitches":658,"strikes":347,"batters_faced":172,"era":8.89,"whip":2.86,"strike_pct":0.527},{"team":"2026 Covered Bridge Riverjaxx 9U","number":7,"player":"Christian H","games_pitched":12,"ip":16.2,"h":31,"r":25,"er":25,"bb":21,"so":16,"pitches":350,"strikes":188,"batters_faced":100,"era":9.0,"whip":3.12,"strike_pct":0.537},{"team":"WV Patriots","number":2,"player":"Eli M","games_pitched":1,"ip":0.2,"h":0,"r":1,"er":1,"bb":3,"so":1,"pitches":23,"strikes":7,"batters_faced":4,"era":9.0,"whip":4.5,"strike_pct":0.304},{"team":"TP FURY 9U","number":30,"player":"Drew M","games_pitched":6,"ip":13.2,"h":23,"r":21,"er":21,"bb":9,"so":14,"pitches":211,"strikes":130,"batters_faced":70,"era":9.22,"whip":2.34,"strike_pct":0.616},{"team":"TP FURY 9U","number":22,"player":"Hayes H","games_pitched":6,"ip":13.1,"h":22,"r":21,"er":21,"bb":15,"so":12,"pitches":252,"strikes":136,"batters_faced":71,"era":9.45,"whip":2.78,"strike_pct":0.54},{"team":"Morgantown Mambas (Gold) 9U","number":1,"player":"Ace Gilbert","games_pitched":16,"ip":24.0,"h":55,"r":48,"er":38,"bb":31,"so":33,"pitches":597,"strikes":325,"batters_faced":148,"era":9.5,"whip":3.58,"strike_pct":0.544},{"team":"Mon River Mudcats 9U","number":42,"player":"Jack S","games_pitched":3,"ip":4.1,"h":7,"r":11,"er":7,"bb":8,"so":5,"pitches":118,"strikes":62,"batters_faced":29,"era":9.69,"whip":3.46,"strike_pct":0.525},{"team":"WV Miners","number":27,"player":"Graesin K","games_pitched":4,"ip":4.2,"h":11,"r":10,"er":8,"bb":5,"so":4,"pitches":93,"strikes":54,"batters_faced":29,"era":10.29,"whip":3.43,"strike_pct":0.581},{"team":"WV Miners","number":5,"player":"Case S","games_pitched":5,"ip":5.0,"h":5,"r":9,"er":9,"bb":13,"so":3,"pitches":126,"strikes":53,"batters_faced":30,"era":10.8,"whip":3.6,"strike_pct":0.421},{"team":"2026 Covered Bridge Riverjaxx 9U","number":11,"player":"Harper H","games_pitched":4,"ip":3.2,"h":13,"r":8,"er":7,"bb":3,"so":5,"pitches":89,"strikes":48,"batters_faced":28,"era":11.45,"whip":4.36,"strike_pct":0.539},{"team":"WV Miners","number":11,"player":"Rhett C","games_pitched":5,"ip":7.2,"h":16,"r":15,"er":15,"bb":10,"so":7,"pitches":172,"strikes":90,"batters_faced":48,"era":11.74,"whip":3.39,"strike_pct":0.523},{"team":"Morgantown Mambas (Gold) 9U","number":0,"player":"Carter Huffman","games_pitched":21,"ip":39.1,"h":63,"r":78,"er":77,"bb":55,"so":64,"pitches":949,"strikes":508,"batters_faced":243,"era":11.75,"whip":3.0,"strike_pct":0.535},{"team":"Morgantown Mambas (Gold) 9U","number":25,"player":"Reid Tiberi","games_pitched":13,"ip":13.0,"h":28,"r":23,"er":27,"bb":23,"so":18,"pitches":331,"strikes":164,"batters_faced":89,"era":12.46,"whip":3.92,"strike_pct":0.495},{"team":"WV Miners","number":14,"player":"Daniel D","games_pitched":7,"ip":13.1,"h":38,"r":30,"er":28,"bb":13,"so":10,"pitches":274,"strikes":156,"batters_faced":82,"era":12.6,"whip":3.83,"strike_pct":0.569},{"team":"WV Miners","number":28,"player":"Nolan M","games_pitched":12,"ip":19.0,"h":53,"r":43,"er":40,"bb":14,"so":17,"pitches":419,"strikes":243,"batters_faced":123,"era":12.63,"whip":3.53,"strike_pct":0.58},{"team":"WV Miners","number":44,"player":"Solar C","games_pitched":12,"ip":19.0,"h":33,"r":47,"er":40,"bb":44,"so":28,"pitches":565,"strikes":268,"batters_faced":133,"era":12.63,"whip":4.05,"strike_pct":0.474},{"team":"Mon River Mudcats 9U","number":7,"player":"Abraham P","games_pitched":14,"ip":19.0,"h":34,"r":46,"er":41,"bb":35,"so":33,"pitches":521,"strikes":261,"batters_faced":131,"era":12.95,"whip":3.63,"strike_pct":0.501},{"team":"TP FURY 9U","number":33,"player":"Caiden S","games_pitched":4,"ip":5.1,"h":5,"r":12,"er":12,"bb":9,"so":5,"pitches":98,"strikes":42,"batters_faced":30,"era":13.5,"whip":2.63,"strike_pct":0.429},{"team":"Morgantown Mambas (Gold) 9U","number":13,"player":"Henry Hu","games_pitched":2,"ip":3.2,"h":13,"r":9,"er":9,"bb":2,"so":1,"pitches":58,"strikes":36,"batters_faced":25,"era":14.73,"whip":4.09,"strike_pct":0.621},{"team":"TP FURY 9U","number":3,"player":"Buzz M","games_pitched":9,"ip":13.0,"h":26,"r":34,"er":32,"bb":21,"so":13,"pitches":302,"strikes":153,"batters_faced":86,"era":14.77,"whip":3.62,"strike_pct":0.507},{"team":"TP FURY 9U","number":10,"player":"Bode H","games_pitched":6,"ip":8.2,"h":21,"r":22,"er":22,"bb":7,"so":7,"pitches":167,"strikes":94,"batters_faced":52,"era":15.23,"whip":3.23,"strike_pct":0.563},{"team":"TP FURY 9U","number":7,"player":"Camron C","games_pitched":8,"ip":11.0,"h":33,"r":29,"er":29,"bb":8,"so":13,"pitches":233,"strikes":139,"batters_faced":71,"era":15.82,"whip":3.73,"strike_pct":0.597},{"team":"Morgantown Mambas (Gold) 9U","number":30,"player":"Jamison Groves","games_pitched":20,"ip":29.2,"h":71,"r":80,"er":80,"bb":49,"so":45,"pitches":851,"strikes":436,"batters_faced":207,"era":16.18,"whip":4.04,"strike_pct":0.512},{"team":"TP FURY 9U","number":12,"player":"Carter K","games_pitched":10,"ip":15.0,"h":46,"r":46,"er":43,"bb":18,"so":11,"pitches":350,"strikes":179,"batters_faced":108,"era":17.2,"whip":4.27,"strike_pct":0.511},{"team":"Morgantown Redbirds (2026) 9U","number":13,"player":"Cree P","games_pitched":1,"ip":1.0,"h":2,"r":3,"er":3,"bb":2,"so":0,"pitches":24,"strikes":9,"batters_faced":7,"era":18.0,"whip":4.0,"strike_pct":0.375},{"team":"Morgantown Mambas (Gold) 9U","number":5,"player":"Elijah Harmon","games_pitched":12,"ip":12.1,"h":35,"r":43,"er":43,"bb":25,"so":16,"pitches":349,"strikes":171,"batters_faced":100,"era":20.92,"whip":4.86,"strike_pct":0.49},{"team":"TP FURY 9U","number":2,"player":"Connor B","games_pitched":5,"ip":8.0,"h":20,"r":29,"er":29,"bb":14,"so":17,"pitches":219,"strikes":114,"batters_faced":57,"era":21.75,"whip":4.25,"strike_pct":0.521},{"team":"WV Miners","number":18,"player":"Coen A","games_pitched":7,"ip":7.1,"h":21,"r":30,"er":29,"bb":19,"so":17,"pitches":256,"strikes":119,"batters_faced":62,"era":23.73,"whip":5.45,"strike_pct":0.465},{"team":"2026 Covered Bridge Riverjaxx 9U","number":22,"player":"Walker F","games_pitched":2,"ip":1.2,"h":3,"r":7,"er":7,"bb":5,"so":3,"pitches":51,"strikes":24,"batters_faced":13,"era":25.2,"whip":4.8,"strike_pct":0.471},{"team":"WV Miners","number":74,"player":"Lukah S","games_pitched":4,"ip":3.0,"h":3,"r":15,"er":13,"bb":17,"so":7,"pitches":158,"strikes":60,"batters_faced":32,"era":26.0,"whip":6.67,"strike_pct":0.38},{"team":"TP FURY 9U","number":5,"player":"Lincoln S","games_pitched":5,"ip":5.1,"h":22,"r":31,"er":31,"bb":15,"so":5,"pitches":214,"strikes":100,"batters_faced":52,"era":34.88,"whip":6.94,"strike_pct":0.467},{"team":"TP FURY 9U","number":13,"player":"Colin S","games_pitched":2,"ip":1.1,"h":6,"r":8,"er":8,"bb":4,"so":2,"pitches":37,"strikes":19,"batters_faced":14,"era":36.0,"whip":7.5,"strike_pct":0.514},{"team":"2026 Covered Bridge Riverjaxx 9U","number":2,"player":"Maxon M","games_pitched":1,"ip":0.1,"h":2,"r":2,"er":2,"bb":2,"so":0,"pitches":17,"strikes":8,"batters_faced":4,"era":36.0,"whip":12.0,"strike_pct":0.471},{"team":"Morgantown Mambas (Gold) 9U","number":2,"player":"Pierson Lehman","games_pitched":2,"ip":1.1,"h":7,"r":9,"er":9,"bb":5,"so":2,"pitches":66,"strikes":32,"batters_faced":16,"era":40.5,"whip":9.0,"strike_pct":0.485},{"team":"2026 Covered Bridge Riverjaxx 9U","number":0,"player":"Arlo B","games_pitched":2,"ip":0.2,"h":2,"r":5,"er":5,"bb":3,"so":1,"pitches":24,"strikes":11,"batters_faced":7,"era":45.0,"whip":7.5,"strike_pct":0.458},{"team":"Morgantown Mambas (Gold) 9U","number":3,"player":"Cruz Cooney","games_pitched":1,"ip":0.1,"h":2,"r":6,"er":6,"bb":3,"so":1,"pitches":34,"strikes":12,"batters_faced":8,"era":108.0,"whip":15.0,"strike_pct":0.353},{"team":"TP FURY 9U","number":1,"player":"Hank B","games_pitched":1,"ip":0.1,"h":3,"r":7,"er":7,"bb":5,"so":0,"pitches":32,"strikes":10,"batters_faced":9,"era":126.0,"whip":24.0,"strike_pct":0.313}]